sweer/__init__.py
sweer/browser_manager.py
sweer/client.py
sweer/config.py
sweer/server.py
sweer/utils.py
sweer-1.0.0.dev5.dist-info/licenses/LICENSE.md
sweer-1.0.0.dev5.dist-info/METADATA
sweer-1.0.0.dev5.dist-info/WHEEL
sweer-1.0.0.dev5.dist-info/entry_points.txt
sweer-1.0.0.dev5.dist-info/top_level.txt
sweer-1.0.0.dev5.dist-info/RECORD
