Metadata-Version: 2.4
Name: sweer
Version: 1.0.0.dev5
Summary: ACI for websites
Author-email: SWE-bench team <support@swebench.com>
License: MIT License
Keywords: nlp,agents,code
Classifier: Operating System :: OS Independent
Classifier: Intended Audience :: Developers
Classifier: License :: OSI Approved :: MIT License
Classifier: Programming Language :: Python :: 3.9
Classifier: Programming Language :: Python :: 3 :: Only
Requires-Python: >=3.9
License-File: LICENSE.md
Requires-Dist: flask
Requires-Dist: playwright
Requires-Dist: requests
Requires-Dist: click
Provides-Extra: dev
Requires-Dist: pytest; extra == "dev"
Requires-Dist: pytest-cov; extra == "dev"
Requires-Dist: pre-commit; extra == "dev"
Dynamic: license-file
